{
    "id" : "heavy_sword",
    "name" : "重剑",
    "material" : "STONE_SWORD",
    "lore" : [
        "§m -50%横扫伤害",
        "§q +30%单体伤害",
        "§m 降低你的移动速度"
    ],
    "baseAttributes" : {
        "GENERIC_ATTACK_DAMAGE" : 12.0,
        "GENERIC_ATTACK_SPEED" : 0.40,
        "GENERIC_MOVEMENT_SPEED" : -0.10
    },
    "star" : [
        {
            "items" : [
                {
                    "material" : "DIAMOND",
                    "amount" : 1
                }
            ],
            "attributes" : [
                {
                    "name" : "GENERIC_ATTACK_DAMAGE",
                    "amount" : 2.5
                }
            ]
        }
    ]
}